dibisoreporting/__init__.py
dibisoreporting/_version.py
dibisoreporting/dibisoreporting.py
dibisoreporting/utils.py
dibisoreporting/biso/__init__.py
dibisoreporting/biso/biso.py
dibisoreporting/pubpart/__init__.py
dibisoreporting/pubpart/pubpart.py
dibisoreporting-0.8.dist-info/licenses/LICENSE.txt
dibisoreporting-0.8.dist-info/METADATA
dibisoreporting-0.8.dist-info/WHEEL
dibisoreporting-0.8.dist-info/top_level.txt
dibisoreporting-0.8.dist-info/RECORD
