Metadata-Version: 2.4
Name: dibisoreporting
Version: 0.8
Summary: A Python library for generating bibliometric reports, developed at the DiBISO.
Author-email: Romain Thomas <contact@romainthomas.net>
License-Expression: GPL-3.0-only
Project-URL: Homepage, https://pypi.org/project/dibisoreporting/
Project-URL: Repository, https://github.com/dibiso-upsaclay/dibisoreporting
Project-URL: Documentation, https://dibiso-upsaclay.github.io/dibisoreporting/
Keywords: DiBISO,Data analysis,Scientific research,Plotly,LaTeX
Classifier: Development Status :: 4 - Beta
Classifier: Intended Audience :: Science/Research
Classifier: Programming Language :: Python
Classifier: Programming Language :: Python :: 3
Classifier: Topic :: Scientific/Engineering :: Visualization
Classifier: Topic :: Text Processing :: Markup :: LaTeX
Classifier: Typing :: Typed
Requires-Python: >=3.10
License-File: LICENSE.txt
Requires-Dist: dibisoplot>=0.7
Requires-Dist: requests
Requires-Dist: pdfCropMargins
Requires-Dist: pypdf
Requires-Dist: kaleido==0.2.1
Dynamic: license-file
